let_me_answer_for_you/__init__.py
let_me_answer_for_you/_nbdev.py
let_me_answer_for_you/chatbot.py
let_me_answer_for_you/dialog_system.py
let_me_answer_for_you/settings.py
let_me_answer_for_you/tests.py
let_me_answer_for_you-0.1.2.dist-info/LICENSE
let_me_answer_for_you-0.1.2.dist-info/METADATA
let_me_answer_for_you-0.1.2.dist-info/WHEEL
let_me_answer_for_you-0.1.2.dist-info/entry_points.txt
let_me_answer_for_you-0.1.2.dist-info/top_level.txt
let_me_answer_for_you-0.1.2.dist-info/RECORD
