Metadata-Version: 2.1
Name: let-me-answer-for-you
Version: 0.1.2
Summary: Question Answering Dialog System
Home-page: https://github.com/kikejimenez/let_me_answer_for_you/tree/master/
Author: E Jimenez
Author-email: ejimenez@intekglobal.com
License: Apache Software License 2.0
Keywords: Machine Learning,Dialog Systems
Platform: UNKNOWN
Classifier: Development Status :: 3 - Alpha
Classifier: Intended Audience :: Developers
Classifier: License :: OSI Approved :: Apache Software License
Classifier: Natural Language :: English
Classifier: Programming Language :: Python :: 3.6
Classifier: Programming Language :: Python :: 3.7
Classifier: Programming Language :: Python :: 3.8
Requires-Python: >=3.6
Requires-Dist: deeppavlov
